lolopy/__init__.py
lolopy/__version__.py
lolopy/learners.py
lolopy/loloserver.py
lolopy/metrics.py
lolopy/utils.py
lolopy/jar/lolo-jar-with-dependencies.jar
lolopy-3.0.7.dist-info/METADATA
lolopy-3.0.7.dist-info/WHEEL
lolopy-3.0.7.dist-info/top_level.txt
lolopy-3.0.7.dist-info/RECORD
