Metadata-Version: 2.2
Name: lolopy
Version: 3.0.7
Summary: Python wrapper for the Lolo machine learning library
Home-page: https://github.com/CitrineInformatics/lolo
Maintainer: Maxwell Venetos
Maintainer-email: mvenetos@citrine.io
Classifier: Programming Language :: Python :: 3
Classifier: Programming Language :: Python :: 3.9
Classifier: Programming Language :: Python :: 3.10
Classifier: Programming Language :: Python :: 3.11
Classifier: Programming Language :: Python :: 3.12
Classifier: Programming Language :: Python :: 3.13
Requires-Python: >=3.9
Requires-Dist: numpy>=1.21
Requires-Dist: scikit-learn<1.7,>=1.3.2
Requires-Dist: py4j<0.10.10,>=0.10.9
Provides-Extra: tests
Requires-Dist: pytest; extra == "tests"
Dynamic: classifier
Dynamic: description
Dynamic: description-content-type
Dynamic: home-page
Dynamic: maintainer
Dynamic: maintainer-email
Dynamic: provides-extra
Dynamic: requires-dist
Dynamic: requires-python
Dynamic: summary
